yabte/__init__.py
yabte/backtest/__init__.py
yabte/backtest/_helpers.py
yabte/backtest/asset.py
yabte/backtest/book.py
yabte/backtest/order.py
yabte/backtest/strategy.py
yabte/backtest/strategyrunner.py
yabte/backtest/transaction.py
yabte/tests/__init__.py
yabte/tests/_helpers.py
yabte/tests/_unittest_numpy_extensions.py
yabte/tests/data/nasdaq/AAPL.csv
yabte/tests/data/nasdaq/AMZN.csv
yabte/tests/data/nasdaq/GOOG.csv
yabte/tests/data/nasdaq/INTC.csv
yabte/tests/data/nasdaq/META.csv
yabte/tests/data/nasdaq/MSFT.csv
yabte/tests/data/nasdaq/NFLX.csv
yabte/tests/data/nasdaq/TSLA.csv
yabte/tests/test_notebooks.py
yabte/tests/test_portopt.py
yabte/tests/test_simulation.py
yabte/tests/test_strategy_runner.py
yabte/tests/test_utilities.py
yabte/utilities/__init__.py
yabte/utilities/lagrangian.py
yabte/utilities/pandas_extension.py
yabte/utilities/plot/__init__.py
yabte/utilities/plot/matplotlib/__init__.py
yabte/utilities/plot/matplotlib/marker_updater.py
yabte/utilities/plot/matplotlib/strategy_runner.py
yabte/utilities/plot/plotly/__init__.py
yabte/utilities/plot/plotly/strategy_runner.py
yabte/utilities/portopt/__init__.py
yabte/utilities/portopt/hierarchical_risk_parity.py
yabte/utilities/portopt/inverse_volatility.py
yabte/utilities/portopt/minimum_variance.py
yabte/utilities/simulation/__init__.py
yabte/utilities/simulation/geometric_brownian_motion.py
yabte/utilities/simulation/heston.py
yabte/utilities/simulation/weiner.py
yabte/utilities/strategy_helpers.py
yabte-0.4.1.dist-info/LICENSE
yabte-0.4.1.dist-info/METADATA
yabte-0.4.1.dist-info/WHEEL
yabte-0.4.1.dist-info/RECORD
