Metadata-Version: 2.1
Name: yabte
Version: 0.4.1
Summary: Yet another backtesting engine
Home-page: https://github.com/bsdz/yabte
License: MIT
Author: Blair Azzopardi
Author-email: blairuk@gmail.com
Requires-Python: >=3.10,<3.13
Classifier: License :: OSI Approved :: MIT License
Classifier: Programming Language :: Python :: 3
Classifier: Programming Language :: Python :: 3.10
Classifier: Programming Language :: Python :: 3.11
Requires-Dist: mypy (>=1.8.0,<2.0.0)
Requires-Dist: pandas (>=2.2.1,<3.0.0)
Requires-Dist: pandas-stubs (>=2.1.4.231227,<3.0.0.0)
Requires-Dist: scipy (>=1.10.0,<2.0.0)
Project-URL: Repository, https://github.com/bsdz/yabte
